{
  "__resolveType": "site/apps/site.ts",
  "routes": [
    {
      "__resolveType": "website/loaders/pages.ts"
    }
  ],
  "seo": {
    "descriptionTemplate": "%s",
    "type": "website",
    "title": "Sandbox",
    "titleTemplate": "%s | vitoo",
    "description": "Just a website",
    "image": "https://ozksgdmyrqcxcwhnbepg.supabase.co/storage/v1/object/public/assets/11909/92ad2099-de19-4953-9fa9-63e1d25e8b27",
    "favicon": "https://ozksgdmyrqcxcwhnbepg.supabase.co/storage/v1/object/public/assets/11909/02992aba-0fa8-4eaa-8687-58c55c1fd5ee"
  },
  "global": [],
  "caching": {
    "directives": []
  },
  "firstByteThresholdMS": true,
  "abTesting": {
    "replaces": [],
    "includeScriptsToHead": {
      "includes": []
    }
  },
  "flavor": {
    "framework": "htmx"
  }
}